LidamaoToolkit.py
LidamaoToolkit-0.13.dist-info/LICENSE
LidamaoToolkit-0.13.dist-info/METADATA
LidamaoToolkit-0.13.dist-info/WHEEL
LidamaoToolkit-0.13.dist-info/top_level.txt
LidamaoToolkit-0.13.dist-info/RECORD
